{
  "book": "Hosea",
  "bookNumber": 28,
  "chapter": 4,
  "verses": [
    {
      "verse": 1,
      "text": "ኣቱም ደቂ እስራኤል፣ ቃል እግዚኣብሄር ስምዑ፣ ሓቅን ሳህልን ፍልጠት ኣምላኽን ኣብታ ሃገር የልቦን እሞ፣ እግዚኣብሄር ምስቶም ኣብታ ሃገር ዚነብሩ ዘለዉ ነገር ኣለዎ።"
    },
    {
      "verse": 2,
      "text": "መርገምን ሓሶትን ቅትለትን ስርቅን ምንዝርናን ገነነ፣ ደም ንደም ተጻናበረ።"
    },
    {
      "verse": 3,
      "text": "ስለዚ እታ ሃገር ክትሐዝን፣ እቶም ኣብኣ ዚነብሩ ዅላቶም ምስ ኣራዊት መሮርም ኣዕዋፍ ሰማይን ኬሕለልዉ፣ ዓሳ ባሕሪውን ኪውድኡ እዮም።"
    },
    {
      "verse": 4,
      "text": "ህዝብኻ ኸምቲ ምስ ካህን ዚካታዕ እዩ፣ እምብኣርሲ ሓደ እኳ ኣይካታዕ፣ ሓደ እኳ ኣይግናሕ።"
    },
    {
      "verse": 5,
      "text": "ንስኻ ብመዓልቲ ኽትወድቕ ኢኻ፣ እቲ ነብዪ ኸኣ ምሳኻ ብለይቲ ኺወድቕ እዩ፣ ኣነውን ነዴኻ ኽድምስሳ እየ።"
    },
    {
      "verse": 6,
      "text": "ህዝበይ ሰኣን ፍልጠት ይጠፍእ። ፍልጠት ስለ ዝኣቤኻ፣ ኣነ ድማ ካህን ከይትዀነኒ ኽኣብየካ እየ። ሕጊ ኣምላኽካ ስለ ዝረሳዕካ፣ ኣነ ኸኣ ንደቅኻ ኽርስዖም እየ።"
    },
    {
      "verse": 7,
      "text": "ብመጠን እቲ ምብዛሖም ከምኡ ኣብዚሖም በደሉኒ። ኣነ ንኽብረቶም ናብ ነውሪ ክልውጦ እየ።"
    },
    {
      "verse": 8,
      "text": "ሓጢኣት ህዝበይ ይቕለቡ፣ ልቦም ድማ ናብ ኣበሳኦም የድህብ ኣሎ።"
    },
    {
      "verse": 9,
      "text": "እቲ ካህን ከኣ ከምቲ ህዝቢ ኪኸውን እዩ፣ ኣነ ድማ ብሰሪ ኣካይዳኦም ክቐጽዖም፣ ግብሮምውን ክመልሰሎም እየ።"
    },
    {
      "verse": 10,
      "text": "ንእግዚኣብሄር ምስዓብ ሓዲጎም እዮም እሞ፣ ይበልዑ ኣይጸግቡን ከኣ፣ ይምንዝሩ ኣይበዝሑን ድማ።"
    },
    {
      "verse": 11,
      "text": "ምንዝርናን ወይንን ኰልዒ ወይንን ኣእምሮ የጥፍእ።"
    },
    {
      "verse": 12,
      "text": "መንፈስ ምንዝርናን ኣስሒትዎም፣ ካብ ኣምላኾም ርሒቖም መንዚሮም እዮም እሞ፣ ህዝበይ ነቲ ዕጨይቲ ይሐትት፣ በትሩውን ይነግሮ።"
    },
    {
      "verse": 13,
      "text": "ኣብ ርእሲ ኣኽራን ይስውኡ፣ ኣብ ልዕሊ ዅርባታት ከኣ፣ ኣብ ትሕቲ ኣውሕን ስየን ጽሕድን፣ ጽላሎም ጽቡቕ እዩ እሞ፣ ይዐጥኑ። ስለዚ ኣዋልድኩም ይምንዝራ፣ መራዕኹም ድማ ይዝምዋ።"
    },
    {
      "verse": 14,
      "text": "ንሳቶም ከኣ ምስ ኣመናዝር የግልሱ፣ ምስ ዘመውቲ ኣንስቲውን ይስውኡ ኣለዉ እሞ፣ ኣዋልድኩም ምስ ኣመንዘራ መራዕኹምውን ምስ ዘመዋ፣ ኣነ ኣይክቐጽዔንን እየ። ኣእምሮ ዜብሉ ህዝብስ ኪውድቕ እዩ።"
    },
    {
      "verse": 15,
      "text": "ኣታ እስራኤል፣ ንስኻ እንተ መንዘርካ፣ ይሁዳ ኣይበድል። ናብ ጊልጋል ኣይትእተዉ፣ ናብ ቤት-ኣዌን ድማ ኣይትውጹኡ፣ ህያው እግዚኣብሄር ኢልኩም ከኣ ኣይትምሐሉ።"
    },
    {
      "verse": 16,
      "text": "እስራኤል ከም ሕንግድ ኣርሒ ሐንጊዱ እዩ እሞ፣ ሕጂ እግዚኣብሄር ከም ዕየት ኣብ ገፊሕ ቦታ ኺጓስዮ እዩ።"
    },
    {
      "verse": 17,
      "text": "ኤፍሬም ምስ ጣኦታት ሐቢሩ እዩ፣ ሕደጎ።"
    },
    {
      "verse": 18,
      "text": "ስኽራኖም ይገድድ ኣሎ፣ ምንዝርና የብዝሑ፣ ሓላቑኣ ኣዝዮም ነውሪ ይፈትዉ።"
    },
    {
      "verse": 19,
      "text": "ንፋስ በኽናፉ ይኣስራ፣ ንሳቶምውን ብመስዋእቶም ኪሐንኩ እዮም።"
    }
  ]
}