{
  "book": "Luke",
  "bookNumber": 42,
  "chapter": 8,
  "verses": [
    {
      "verse": 1,
      "text": "ከዚህም በኋላ እየሰበከና ስለ እግዚአብሔር መንግሥት የምሥራች እየተናገረ በየከተማይቱ በየመንደሩም ያልፍ ነበር፤"
    },
    {
      "verse": 2,
      "text": "አሥራ ሁለቱም ከእርሱ ጋር ነበሩ፥ ከክፉዎች መናፍስትና ከደዌም ተፈውሰው የነበሩ አንዳንድ ሴቶች፤ እነርሱም ሰባት አጋንንት የወጡላት መግደላዊት የምትባል ማርያም፥"
    },
    {
      "verse": 3,
      "text": "የሄሮድስ አዛዥ የኩዛ ሚስት ዮሐናም ሶስናም ብዙዎች ሌሎችም ሆነው በገንዘባቸው ያገለግሉት ነበር።"
    },
    {
      "verse": 4,
      "text": "ብዙ ሕዝብም በተሰበሰቡ ጊዜ ከከተማዎችም ሁሉ ወደ እርሱ በመጡ ጊዜ በምሳሌ እንዲህ ሲል ተናገራቸው።"
    },
    {
      "verse": 5,
      "text": "ዘሪ ዘሩን ሊዘራ ወጣ። ሲዘራም አንዳንዱ በመንገድ ዳር ወደቀ ተረገጠም፥ የሰማይ ወፎችም በሉት።"
    },
    {
      "verse": 6,
      "text": "ሌላውም በዓለት ላይ ወደቀ፥ በበቀለም ጊዜ እርጥበት ስላልነበረው ደረቀ።"
    },
    {
      "verse": 7,
      "text": "ሌላውም በእሾህ መካከል ወደቀ፥ እሾሁም አብሮ በቀለና አነቀው።"
    },
    {
      "verse": 8,
      "text": "ሌላውም በመልካም መሬት ላይ ወደቀ፤ በበቀለም ጊዜ መቶ እጥፍ አፈራ። ይህን በተናገረ ጊዜ። የሚሰማ ጆሮ ያለው ይስማ ብሎ ጮኸ።"
    },
    {
      "verse": 9,
      "text": "ደቀ መዛሙርቱም። ይህ ምሳሌ ምንድር ነው? ብለው ጠየቁት።"
    },
    {
      "verse": 10,
      "text": "እርሱም እንዲህ አለ። ለእናንተ የእግዚአብሔርን መንግሥት ምሥጢር ማወቅ ተሰጥቶአችኋል፤ ለሌሎች ግን እያዩ እንዳያዩ እየሰሙም እንዳያስተውሉ በምሳሌ ነው።"
    },
    {
      "verse": 11,
      "text": "ምሳሌው ይህ ነው። ዘሩ የእግዚአብሔር ቃል ነው።"
    },
    {
      "verse": 12,
      "text": "በመንገድ ዳርም ያሉት የሚሰሙ ናቸው፤ ከዚህ በኋላም ዲያብሎስ ይመጣል አምነውም እንዳይድኑ ቃሉን ከልባቸው ይወስዳል።"
    },
    {
      "verse": 13,
      "text": "በዓለት ላይም ያሉት ሲሰሙ ቃሉን በደስታ የሚቀበሉ ናቸው፤ እነርሱም ለጊዜው ብቻ ያምናሉ እንጂ በፈተና ጊዜ የሚክዱ ሥር የሌላቸው ናቸው።"
    },
    {
      "verse": 14,
      "text": "በእሾህ መካከልም የወደቀ እነዚህ የሚሰሙት ናቸው፤ መንገዳቸውንም ሄደው በሕይወት ዘመን በአሳብና በባለ ጠግነት ምቾት ይታነቃሉ፥ ሙሉ ፍሬም አያፈሩም።"
    },
    {
      "verse": 15,
      "text": "በመልካም መሬት ላይም የወደቀ እነርሱ በመልካምና በበጎ ልብ ቃሉን ሰምተው የሚጠብቁት በመጽናትም ፍሬ የሚያፈሩ ናቸው።"
    },
    {
      "verse": 16,
      "text": "መብራትንም አብርቶ በዕቃ የሚከድነው ወይም ከአልጋ በታች የሚያኖረው የለም፥ የሚገቡት ሰዎች ብርሃኑን እንዲያዩ በመቅረዝ ላይ ያኖረዋል እንጂ።"
    },
    {
      "verse": 17,
      "text": "የማይገለጥ የተሰወረ የለምና፥ የማይታወቅም ወደ ግልጥም የማይመጣ የተሸሸገ የለም።"
    },
    {
      "verse": 18,
      "text": "እንግዲህ እንዴት እንድትሰሙ ተጠበቁ፤ ላለው ሁሉ ይሰጠዋልና፥ ከሌለውም ሁሉ፥ ያው ያለው የሚመስለው እንኳ ይወሰድበታል።"
    },
    {
      "verse": 19,
      "text": "እናቱና ወንድሞቹም ወደ እርሱ መጡ፥ ከሕዝቡም ብዛት የተነሣ ሊያገኙት አልተቻላቸውም።"
    },
    {
      "verse": 20,
      "text": "እናትህና ወንድሞችህ ሊያዩህ ወድደው በውጭ ቆመዋል ብለው ነገሩት።"
    },
    {
      "verse": 21,
      "text": "እርሱም መልሶ። እናቴና ወንድሞቼስ የእግዚአብሔርን ቃል ሰምተው የሚያደርጉት እነዚህ ናቸው አላቸው።"
    },
    {
      "verse": 22,
      "text": "ከዕለታቱም በአንዱ እርሱ ከደቀ መዛሙርቱ ጋር ወደ ታንኳ ገብቶ። ወደ ባሕር ማዶ እንሻገር አላቸው፤ ተነሡም።"
    },
    {
      "verse": 23,
      "text": "ሲሄዱም አንቀላፋ። ዓውሎ ነፋስም በባሕር ላይ ወረደ፥ ውኃውም ታንኳይቱን ይሞላ ነበርና ይጨነቁ ነበር።"
    },
    {
      "verse": 24,
      "text": "ቀርበውም። አቤቱ፥ አቤቱ ጠፋን እያሉ አስነሡት። እርሱም ነቅቶ ነፋሱንና የውኃውን ማዕበል ገሠጻቸው፤ ተዉም፥ ጽጥታም ሆነ።"
    },
    {
      "verse": 25,
      "text": "እርሱም። እምነታችሁ የት ነው? አላቸው። ፈርተውም ተደነቁ፥ እርስ በርሳቸውም። እንዲህ ነፋሳትንና ውኃን እንኳ የሚያዝ ለእርሱም የሚታዘዙለት ይህ ማን ነው? አሉ።"
    },
    {
      "verse": 26,
      "text": "በገሊላም አንጻር ወዳለችው ወደ ጌርጌሴኖን አገር በታንኳ ደረሱ።"
    },
    {
      "verse": 27,
      "text": "ወደ ምድርም በወጣ ጊዜ አጋንንት ያደሩበት አንድ ሰው ከከተማ ወጥቶ ተገናኘው፥ ከብዙ ዘመንም ጀምሮ ልብስ ሳይለብስ በመቃብር እንጂ በቤት አይኖርም ነበር።"
    },
    {
      "verse": 28,
      "text": "ኢየሱስንም ባየ ጊዜ ጮኾ በፊቱ ተደፋ በታላቅ ድምፅም። የልዑል እግዚአብሔር ልጅ ኢየሱስ ሆይ፥ ከአንተ ጋር ምን አለኝ? እንዳትሣቀየኝ እለምንሃለሁ አለ።"
    },
    {
      "verse": 29,
      "text": "ርኵሱን መንፈስ ከሰውዬው እንዲወጣ ያዘው ነበርና። ብዙ ዘመንም ይዞት ነበርና፥ በሰንሰለትና በእግር ብረትም ታስሮ ይጠበቅ ነበር፤ እስራቱንም ሰብሮ በጋኔኑ ወደ ምድረ በዳ ይነዳ ነበር።"
    },
    {
      "verse": 30,
      "text": "ኢየሱስም። ስምህ ማን ነው? ብሎ ጠየቀው። እርሱም ብዙዎች አጋንንት ገብተውበት ነበርና። ሌጌዎን አለው።"
    },
    {
      "verse": 31,
      "text": "ወደ ጥልቁም ሊሄዱ እንዳያዛቸው ለመኑት።"
    },
    {
      "verse": 32,
      "text": "በዚያም በተራራው የብዙ እሪያ መንጋ ይሰማሩ ነበር፤ ወደ እነርሱም ሊገቡ እንዲፈቅድላቸው ለመኑት፤ ፈቀደላቸውም።"
    },
    {
      "verse": 33,
      "text": "አጋንንትም ከሰውዬው ወጥተው ወደ እሪያዎች ገቡ፥ መንጋውም ከአፋፉ ወደ ባሕር ተጣደፉና ሰጠሙ።"
    },
    {
      "verse": 34,
      "text": "እረኞችም የሆነውን ባዩ ጊዜ ሸሽተው በከተማውና በአገሩ አወሩት።"
    },
    {
      "verse": 35,
      "text": "የሆነውን ነገር ሊያዩ ወጥተውም ወደ ኢየሱስ መጡ፥ አጋንንትም የወጡለትን ሰው ለብሶ ልቡም ተመልሶ በኢየሱስ እግር አጠገብ ተቀምጦ አገኙትና ፈሩ።"
    },
    {
      "verse": 36,
      "text": "ያዩትም ደግሞ አጋንንት ያደሩበት ሰው እንዴት እንደ ዳነ አወሩላቸው።"
    },
    {
      "verse": 37,
      "text": "በዙሪያውም በጌርጌሴኖን አገር ያሉት ሕዝብ ሁሉ ታላቅ ፍርሃት ይዞአቸዋልና ከእነርሱ እንዲሄድ ለመኑት በታንኳም ገብቶ ተመለሰ።"
    },
    {
      "verse": 38,
      "text": "አጋንንት የወጡለት ሰውም ከእርሱ ጋር ይኖር ዘንድ ለመነው፤"
    },
    {
      "verse": 39,
      "text": "ነገር ግን። ወደ ቤትህ ተመለስ፥ እግዚአብሔር እንዴት ያለ ታላቅ ነገር እንዳደረግልህ ንገር ብሎ አሰናበተው። ኢየሱስም እንዴት ያለ ታላቅ ነገር እንዳደረገለት በከተማው ሁሉ እየሰበከ ሄደ።"
    },
    {
      "verse": 40,
      "text": "ኢየሱስም በተመለሰ ጊዜ ሁሉ ይጠብቁት ነበርና ሕዝቡ ተቀበሉት።"
    },
    {
      "verse": 41,
      "text": "እነሆም፥ ኢያኢሮስ የሚባል ሰው መጣ፥ እርሱም የምኵራብ አለቃ ነበረ በኢየሱስም እግር ላይ ወድቆ ወደ ቤቱ እንዲገባ ለመነው፤"
    },
    {
      "verse": 42,
      "text": "አሥራ ሁለት ዓመት የሆናት አንዲት ሴት ልጅ ነበረችውና፤ እርስዋም ለሞት ቀርባ ነበረች። ሲሄድም ሕዝቡ ያጨናንቁት ነበር።"
    },
    {
      "verse": 43,
      "text": "ከአሥራ ሁለት ዓመትም ጀምሮ ደም የሚፈሳት ሴት ነበረች፥ ትዳርዋንም ሁሉ ለባለመድኃኒቶች ከስራ ማንም ሊፈውሳት አልተቻለውም።"
    },
    {
      "verse": 44,
      "text": "በኋላውም ቀርባ የልብሱን ጫፍ ዳሰሰች፥ የደምዋም ፈሳሽ በዚያን ጊዜ ቆመ።"
    },
    {
      "verse": 45,
      "text": "ኢየሱስም። የዳሰሰኝ ማን ነው? አለ። ሁሉም በካዱ ጊዜ፥ ጴጥሮስና ከእርሱ ጋር የነበሩት። አቤቱ፥ ሕዝቡ ያጫንቁሃልና ያጋፉህማል፤ የዳሰሰኝ ማን ነው ትላለህን? አሉ።"
    },
    {
      "verse": 46,
      "text": "ኢየሱስ ግን። አንድ ሰው ዳስሶኛል፥ ኃይል ከእኔ እንደ ወጣ እኔ አውቃለሁና አለ።"
    },
    {
      "verse": 47,
      "text": "ሴቲቱም እንዳልተሰወረች ባየች ጊዜ እየተንቀጠቀጠች መጥታ በፊቱ ተደፋች፥ በምን ምክንያትም እንደ ዳሰሰችው ፈጥናም እንደ ተፈወሰች በሕዝቡ ሁሉ ፊት አወራች።"
    },
    {
      "verse": 48,
      "text": "እርሱም። ልጄ ሆይ፥ እምነትሽ አድኖሻል፤ በሰላም ሂጂ አላት።"
    },
    {
      "verse": 49,
      "text": "እርሱም ገና ሲናገር አንድ ሰው ከምኵራብ አለቃው ቤት መጥቶ። ልጅህ ሞታለች፤ እንግዲህ መምህሩን አታድክም አለ።"
    },
    {
      "verse": 50,
      "text": "ኢየሱስ ግን ሰምቶ። አትፍራ፤ እመን ብቻ ትድንማለች ብሎ መለሰለት።"
    },
    {
      "verse": 51,
      "text": "ወደ ቤትም ሲገባ ከጴጥሮስና ከያዕቆብ ከዮሐንስም ከብላቴናይቱም አባትና እናት በቀር ማንም ከእርሱ ጋር ይገባ ዘንድ አልፈቀደም።"
    },
    {
      "verse": 52,
      "text": "ሁሉም እያለቀሱላት ዋይ ዋይ ይሉ ነበር። እርሱ ግን። አታልቅሱ፤ ተኝታለች እንጂ አልሞተችም አለ።"
    },
    {
      "verse": 53,
      "text": "እንደ ሞተችም አውቀው በጣም ሳቁበት።"
    },
    {
      "verse": 54,
      "text": "እርሱ ግን እጅዋን ይዞ። አንቺ ብላቴና፥ ተነሺ ብሎ ጮኸ።"
    },
    {
      "verse": 55,
      "text": "ነፍስዋም ተመለሰች፥ ፈጥናም ቆመች፥ የምትበላውንም እንዲሰጡአት አዘዘ።"
    },
    {
      "verse": 56,
      "text": "ወላጆችዋም ተገረሙ፤ እርሱ ግን የሆነውን ለማንም እንዳይነግሩ አዘዛቸው።"
    }
  ]
}