{
  "book": "Galatians",
  "bookNumber": 48,
  "chapter": 2,
  "verses": [
    {
      "verse": 1,
      "text": "ከዚያ ወዲያ ከአሥራ አራት ዓመት በኋላ ከበርናባስ ጋር ቲቶን ደግሞ ይዤ ወደ ኢየሩሳሌም ሁለተኛ ወጣሁ፤"
    },
    {
      "verse": 2,
      "text": "እንደ ተገለጠልኝም ወጣሁ፤ ምናልባትም በከንቱ እንዳልሮጥ ወይም በከንቱ ሮጬ እንዳልሆን በአሕዛብ መካከል የምሰብከውን ወንጌል አስታወቅኋቸው፤ ዋኖች ግን መስለው ለሚታዩ ለብቻቸው አስታወቅኋቸው።"
    },
    {
      "verse": 3,
      "text": "ነገር ግን ከእኔ ጋር የነበረ ቲቶ እንኳ የግሪክ ሰው ሲሆን ይገረዝ ዘንድ ግድ አላሉትም፤"
    },
    {
      "verse": 4,
      "text": "ነገር ግን ባሪያዎች ሊያደርጉን በክርስቶስ ኢየሱስ ያለንን አርነታችንን ይሰልሉ ዘንድ ሾልከው በስውር ስለ ገቡ ስለ ሐሰተኞች ወንድሞች ነበረ።"
    },
    {
      "verse": 5,
      "text": "የወንጌልም እውነት በእናንተ ዘንድ ጸንቶ እንዲኖር ለአንድ ሰዓት እንኳ ለቅቀን አልተገዛንላቸውም።"
    },
    {
      "verse": 6,
      "text": "አለቆች የመሰሉት ግን፥ በፊት ማን እንደ ነበሩ አይገደኝም፤ እግዚአብሔር የሰውን ፊት አይቶ አያደላም፤ አለቆች የመሰሉት አንዳች እንኳ አልጨመሩልኝምና፥"
    },
    {
      "verse": 7,
      "text": "ተመልሰው ግን ጴጥሮስ ለተገረዙት የሆነው ወንጌል አደራ እንደ ተሰጠው እንዲሁ ለእኔ ላልተገረዙት የሆነው ወንጌል አደራ እንደ ተሰጠኝ አዩ፤"
    },
    {
      "verse": 8,
      "text": "ለተገረዙት ሐዋርያ እንዲሆን ለጴጥሮስ የሠራለት፥ ለእኔ ደግሞ ለአሕዛብ ሐዋርያ እንድሆን ሠርቶአልና።"
    },
    {
      "verse": 9,
      "text": "ደግሞ የተሰጠኝን ጸጋ አውቀው፥ አዕማድ መስለው የሚታዩ ያዕቆብና ኬፋ ዮሐንስም እኛ ወደ አሕዛብ እነርሱም ወደ ተገረዙት ይሄዱ ዘንድ ለእኔና ለበርናባስ ቀኝ እጃቸውን ሰጡን፤"
    },
    {
      "verse": 10,
      "text": "ድሆችን እናስብ ዘንድ ብቻ ለመኑን፥ ይህንም ደግሞ ላደርግ ተጋሁ።"
    },
    {
      "verse": 11,
      "text": "ነገር ግን ኬፋ ወደ አንጾኪያ በመጣ ጊዜ ፊት ለፊት ተቃወምሁት፥ ይፈረድበት ዘንድ ይገባ ነበርና።"
    },
    {
      "verse": 12,
      "text": "አንዳንድ ከያዕቆብ ዘንድ ሳይመጡ ከአሕዛብ ጋር አብሮ ይበላ ነበርና፤ በመጡ ጊዜ ግን ከተገረዙት ወገን ያሉትን ፈርቶ ያፈገፍግ ነበርና ከእነርሱ ተለየ።"
    },
    {
      "verse": 13,
      "text": "የቀሩትም አይሁድ ደግሞ፥ በርናባስ ስንኳ በግብዝነታቸው እስከ ተሳበ ድረስ፥ ከእርሱ ጋር አብረው ግብዞች ሆኑ።"
    },
    {
      "verse": 14,
      "text": "ነገር ግን እንደ ወንጌል እውነት በቅንነት እንዳልሄዱ ባየሁ ጊዜ በሁሉ ፊት ኬፋን። አንተ አይሁዳዊ ሳለህ በአይሁድ ኑሮ ያይደለ በአሕዛብ ኑሮ ብትኖር፥ አሕዛብ በአይሁድ ኑሮ ሊኖሩ እንዴት ግድ አልሃቸው? አልሁት።"
    },
    {
      "verse": 15,
      "text": "እኛ በፍጥረት አይሁድ ነን ኃጢአተኞችም የሆኑ አሕዛብ አይደለንም፤"
    },
    {
      "verse": 16,
      "text": "ነገር ግን ሰው በኢየሱስ ክርስቶስ በማመን እንዲጸድቅ እንጂ በሕግ ሥራ እንዳይሆን አውቀን፥ ሥጋን የለበሰ ሁሉ በሕግ ሥራ ስለማይጸድቅ፥ እኛ ራሳችን በሕግ ሥራ ሳይሆን በክርስቶስ እምነት እንጸድቅ ዘንድ በክርስቶስ ኢየሱስ አምነናል።"
    },
    {
      "verse": 17,
      "text": "ነገር ግን በክርስቶስ ልንጸድቅ የምንፈልግ ስንሆን ራሳችን ደግሞ ኃጢአተኞች ሆነን ከተገኘን፥ እንግዲያስ ክርስቶስ የኃጢአት አገልጋይ ነዋ? አይደለም።"
    },
    {
      "verse": 18,
      "text": "ያፈረስሁትን ይህን እንደ ገና የማንጽ ከሆንሁ ራሴ ሕግ ተላላፊ እንድሆን አስረዳለሁና።"
    },
    {
      "verse": 19,
      "text": "እኔ ለእግዚአብሔር ሕያው ሆኜ እኖር ዘንድ በሕግ በኩል ለሕግ ሞቼ ነበርና።"
    },
    {
      "verse": 20,
      "text": "ከክርስቶስ ጋር ተሰቅዬአለሁ፤ እኔም አሁን ሕያው ሆኜ አልኖርም ክርስቶስ ግን በእኔ ይኖራል፤ አሁንም በሥጋ የምኖርበት ኑሮ በወደደኝና ስለ እኔ ራሱን በሰጠው በእግዚአብሔር ልጅ ላይ ባለ እምነት የምኖረው ነው።"
    },
    {
      "verse": 21,
      "text": "የእግዚአብሔርን ጸጋ አልጥልም፤ ጽድቅስ በሕግ በኩል ከሆነ እንኪያስ ክርስቶስ በከንቱ ሞተ።"
    }
  ]
}