{
  "book": "Jeremiah",
  "bookNumber": 24,
  "chapter": 20,
  "verses": [
    {
      "verse": 1,
      "text": "እቲ ኣብ ቤት እግዚኣብሄር ሕልቅነት እተሸመ ጳሽሑር፡ ወዲ እቲ ኻህን ኢሜር፡ ኤርምያስ እዚ ነገር እዚ ኺንበ ኸሎ ሰምዖ።"
    },
    {
      "verse": 2,
      "text": "ጳሽሑር ከኣ ንነብዪ ኤርምያስ ወቕዖ፡ ኣብታ ኣብ ጥቓ ቤት እግዚኣብሄር ዝነበረት ላዕለይቲ ደገ ብንያምውን ኣብ ጒንዲ ኣሰሮ።"
    },
    {
      "verse": 3,
      "text": "ንጽባሒቱ ጳሽሑር ንኤርምያስ ካብ ማእሰርቲ ኣውጽኦ። ኤርምያስ ከኣ፡ እግዚኣብሄር ማጉር ፦ ሚሳቢብ እምበር፡ ጳሽሑር ኢሉ ኣይሰመየካን፡ በሎ።"
    },
    {
      "verse": 4,
      "text": "እምበኣርሲ እግዚኣብሄር ከምዚ ይብል ኣሎ፡ እንሆ፡ ንርእስኻን ንዂሎም ፈተውትኻን መሰምበዲ ኽገብረካ እየ፡ ብሰይፊ ጸላእቶም ኪወድቁ እዮም፡ ኣዒንትኻ ድም ኪጥምታኦ እየን። ንዂላ ይሁዳ ኸኣ ኣብ ኢድ ንጉስ ባቢሎን ክውፍያ እየ፡ ንሱ ድማ ናብ ባቢሎን ኪማርኾም ብሰይፊውን ኪቐትሎም እዩ።"
    },
    {
      "verse": 5,
      "text": "ኲሉ ጥሪት እዛ ኸተማ እዚኣን ኲሉ ጻማኣን ኲሉ ኽቡር ኣቓሑኣን ኲሉ እቲ መዛግብ ነገስታት ይሁዳን ኣብ ኢድ ጸላእቶም ክህቦ እየ። ንሳቶም ድማ ኪዘምትዎ፡ ኪወስድዎ፡ ናብ ባቢሎንውን ኪማርኽዎ እዮም።"
    },
    {
      "verse": 6,
      "text": "ኣታ ጳሽሑር፡ ንስኻን ኣብ ቤትካ ዚነብሩ ዂሎምን ክትማረኹ ኢኹም፡ ናብ ባቢሎን ክትከይድ ኢኻ እሞ፡ ምስቶም ሓሶት እተነቤኻሎም ኲሎም ፈተውትኻ ኣብኡ ኽትመውት፡ ኣብኡውን ክትቅበር ኢኻ።"
    },
    {
      "verse": 7,
      "verseEnd": 8,
      "text": "ብተዛረብኩሉ መጠን እጭርሕ፡ ዓመጽን ዘመተን ኢለ እጭርሕ ኣሎኹ። ቃል እግዚኣብሄር መዓልቲ ብመልኣ ንጸርፍን መላገጽን ኰይኑኒ እዩ እሞ፡ ዎ እግዚኣብሄር፡ ጠበርካኒ ተጠበርኩ ኸኣ፡ ሐየልካኒ ኣሕመቕካኒ ድማ። ኣብ ጸጽባሕ መላገጺ ዀንኩ፡ ኲሎምውን የባጭውለይ ኣለው።"
    },
    {
      "verse": 9,
      "text": "ኣይክዝክሮን፡ ደጊምስ ብስሙ ኣይክዛረብን እየ፡ እኳ እንተ በልኩ፡ ኣብ ዓጻጽምተይ ተዐጽዩ፡ ኣብ ልበይ ከም ዚነድድ ሓዊ ዀነኒ። ክጽመሞ ተጋደልኩ፡ ግናኸ ኣይኰነለይን።"
    },
    {
      "verse": 10,
      "text": "ብዙሓት ኪሐምዩኒ እሰምዕ ኣሎኹ እሞ፡ ብዂሉ ሸነኸይ ስምባድ ይኸበኒ ኣሎ። ክሰስዎ፡ ንሕና ኸኣ ክንከሶ፡ ኢሎም ኲላቶም ፈተውተይ ውድቀተይ ይቃጸዉ፡ ምእንቲ ኸነሕምቖን ሕነ ኽንፈድዮንሲ ይጥበረልና ይኸውን፡ ይብሉ ኣለው።"
    },
    {
      "verse": 11,
      "text": "ግናኸ እግዚኣብሄር ከም ሓያል ጅግና ምሳይ እዩ። ስለዚ እቶም ሰጐጒተይ ተዐንቂፎም ይወድቁ፡ ዚከኣሎምውን የልቦን። ብጥበብ ስለ ዘይገበርዎ ኣዝዮም ኪሐንኩ እዮም፡ ነውሮም ድማ ንሓዋሩ ኣይኪርሳዕን እዩ።"
    },
    {
      "verse": 12,
      "text": "ኣታ ንጻድቕ እትምርምር፡ ልብን ኰላሊትን እትርኢ እግዚኣብሄር ጐይታ ሰራዊት፡ ነገረይ ንኣኻ ኣማዕቊበ እየ እሞ፡ ነቲ እትፈድዮም ሕነ ኣርእየኒ።"
    },
    {
      "verse": 13,
      "text": "ንነፍሲ ድኻ ኻብ ኢድ ገበርቲ እከይ ኣድሒንዋ እዩ እሞ፡ ንእግዚኣብሄር ዘምሩ፡ ንእግዚኣብሄር ወድሱ።"
    },
    {
      "verse": 14,
      "text": "እተወለድኩላ መዓልቲ ርግምቲ ትኹን፡ እታ ኣደይ ንኣይ ዝወለደትላ መዓልቲ ኣይትባረኽ።"
    },
    {
      "verse": 15,
      "text": "እቲ ነቦይ፡ ወዲ ተወሊዱልካ፡ ኢሉ ዘበሰሮ እሞ ዘሐጐሶ ሰብኣይ ርጉም ይኹን።"
    },
    {
      "verse": 16,
      "text": "እቲ ሰብኣይ እቲ ኸምተን እግዚኣብሄር ከይተጣዕሰ ዝገልበጠን ከተማታት ይኹን። ንግሆ ኣውያት፡ ቀትሪ ድማ ጭድርታ ውግእ ይስማዕ።"
    },
    {
      "verse": 17,
      "text": "ኣደይ መቓብረይ ክትከውን፡ ንሓዋሩ ኸኣ ብጥንስታ ኽትነብርሲ፡ ስለምንታይ ኣብ ማሕጸን ወላዲተይ ከሎኹ ዘይቀተለኒ?"
    },
    {
      "verse": 18,
      "text": "ድኻምን ሓዘንን ክርኢ፡ ዕለተይ ከኣ ብሓፍረት ክውድእከ ስለምንታይ ካብ ማሕጸን ወጽእኩ?"
    }
  ]
}