{
  "book": "Exodus",
  "bookNumber": 2,
  "chapter": 7,
  "verses": [
    {
      "verse": 1,
      "text": "እግዚአብሔርም ሙሴን አለው። እይ፥ እኔ ለፈርዖን አምላክ አድርጌሃለሁ፤ ወንድምህም አሮን ነቢይ ይሆንልሃል።"
    },
    {
      "verse": 2,
      "text": "ያዘዝሁህን ነገር ሁሉ አንተ ትነግረዋለህ፤ ወንድምህም አሮን የእስራኤልን ልጆች ከአገሩ ይለቅቅ ዘንድ ከፈርዖን ጋር ይናገራል።"
    },
    {
      "verse": 3,
      "text": "እኔም የፈርዖንን ልብ አጸናለሁ፥ በግብፅ ምድርም ድንቄንና ተአምራቴን አበዛለሁ።"
    },
    {
      "verse": 4,
      "text": "ፈርዖንም አይሰማችሁም፥ እጄንም በግብፅ ላይ አደርጋለሁ፥ ሠራዊቴንም የእስራኤልን ልጆች ሕዝቤን በታላቅ ፍርድ ከግብፅ አገር አወጣለሁ።"
    },
    {
      "verse": 5,
      "text": "ግብፃውያንም፥ እጄን በግብፅ ላይ በዘረጋሁ ጊዜ፥ የእስራኤልንም ልጆች ከመካከላቸው ባወጣሁ ጊዜ፥ እኔ እግዚአብሔር እንደ ሆነሁ ያውቃሉ።"
    },
    {
      "verse": 6,
      "text": "ሙሴና አሮንም እንዲህ አደረጉ፤ እግዚአብሔር እንዳዘዛቸው አደረጉ።"
    },
    {
      "verse": 7,
      "text": "ፈርዖንንም በተናገሩት ጊዜ ሙሴ የሰማንያ ዓመት ሰው ነበረ፥ አሮንም የሰማንያ ሦስት ዓመት ሰው ነበረ።"
    },
    {
      "verse": 8,
      "text": "እግዚአብሔርም ሙሴንና አሮንን እንዲህ ሲል ተናገራቸው።"
    },
    {
      "verse": 9,
      "text": "ፈርዖን። ተአምራትን አሳዩኝ ሲላችሁ፥ አሮንን። በትርህን ወስደህ እባብ እንድትሆን በፈርዖን ፊት ጣላት በለው።"
    },
    {
      "verse": 10,
      "text": "ሙሴና አሮንም ወደ ፈርዖን ገቡ፥ እግዚአብሔርም እንዳዘዛቸው እንዲሁ አደረጉ፤ አሮንም በትሩን በፈርዖንና በባሮቹ ፊት ጣለ፥ እባብም ሆነች።"
    },
    {
      "verse": 11,
      "text": "ፈርዖንም ጠቢባንንና መተተኞችን ጠራ፤ የግብፅም ጠንቋዮች በአስማታቸው እንዲሁ ደግሞ አደረጉ።"
    },
    {
      "verse": 12,
      "text": "እያንዳንዳቸውም በትራቸውን ጣሉ፥ እባቦችም ሆኑ፤ የአሮን በትር ግን በትራቸውን ዋጠች።"
    },
    {
      "verse": 13,
      "text": "እግዚአብሔር እንደ ተናገረ፥ የፈርዖን ልብ ጸና፥ አልሰማቸውምም።"
    },
    {
      "verse": 14,
      "text": "እግዚአብሔርም ሙሴን አለው። የፈርዖን ልብ ደነደነ፥ ሕዝቡንም ለመልቀቅ እንቢ አለ።"
    },
    {
      "verse": 15,
      "text": "ማልደህ ወደ ፈርዖን ሂድ፤ እነሆ ወደ ውኃ ይወጣል፥ ትገናኘውም ዘንድ አንተ በወንዝ ዳር ትቆማለህ፤ እባብም ሆና የተለወጠችውን በትር በእጅህ ትወስዳለህ።"
    },
    {
      "verse": 16,
      "text": "እንዲህም ትለዋለህ። የዕብራውያን አምላክ እግዚአብሔር። በምድረ በዳ እንዲያገለግሉኝ ሕዝቤን ልቀቅ ብሎ ወደ አንተ ላከኝ፤ እነሆም እስከ ዛሬ አልሰማህም።"
    },
    {
      "verse": 17,
      "text": "እግዚአብሔር እንዲህ ይላል። እኔ እግዚአብሔር እንደ ሆንሁ በዚህ ታውቃለህ፤ እነሆ እኔ የወንዙን ውኃ በእጄ ባለችው በትር እመታለሁ፥ ውኃውም ተለውጦ ደም ይሆናል።"
    },
    {
      "verse": 18,
      "text": "በወንዙም ያሉት ዓሦች ይሞታሉ፥ ወንዙም ይገማል፤ ግብፃውያንም የወንዙን ውኃ ለመጠጣት ይጠላሉ።"
    },
    {
      "verse": 19,
      "text": "እግዚአብሔርም ሙሴን አለው። አሮንን። በትርህን ውሰድ፥ ደምም እንዲሆኑ በግብፅ ውኆች በወንዞቻቸውም በመስኖቻቸውም በኩሬዎቻቸውም በውኃ ማከማቻዎቻቸውም ሁሉ ላይ እጅህን ዘርጋ በለው፤ በግብፅም አገር ሁሉ በእንጨት ዕቃና በድንጋይ ዕቃ ሁሉ ደም ይሆናል።"
    },
    {
      "verse": 20,
      "text": "ሙሴና አሮንም እግዚአብሔር እንዳዘዛቸው እንዲሁ አደረጉ፤ በትሩንም አነሣ፥ በፈርዖንና በባሪያዎቹም ፊት የወንዙን ውኃ መታ፤ የወንዙም ውኃ ሁሉ ተለውጦ ደም ሆነ።"
    },
    {
      "verse": 21,
      "text": "በወንዙም የነበሩ ዓሦች ሞቱ፤ ወንዙም ገማ፥ ግብፃውያንም ከወንዙ ውኃ ይጠጡ ዘንድ አልቻሉም ደሙም በግብፅ አገር ሁሉ ነበረ።"
    },
    {
      "verse": 22,
      "text": "የግብፅም ጠንቋዮች በአስማታቸው እንዲሁ አደረጉ፤ እግዚአብሔርም እንደተናገረ የፈርዖን ልብ ጸና፥ አልሰማቸውምም።"
    },
    {
      "verse": 23,
      "text": "ፈርዖንም ተመልሶ ወደ ቤቱ ገባ፥ ይህንም ደግሞ በልቡ አላኖረውም።"
    },
    {
      "verse": 24,
      "text": "ግብፃውያንም ሁሉ የወንዙን ውኃ ይጠጡ ዘንድ አልቻሉምና በወንዙ አጠገብ ውኃ ሊጠጡ ቆፈሩ።"
    },
    {
      "verse": 25,
      "text": "እግዚአብሔርም ወንዙን ከመታ በኋላ ሰባት ቀን ተፈጸመ።"
    }
  ]
}