{
  "book": "Isaiah",
  "bookNumber": 23,
  "chapter": 47,
  "verses": [
    {
      "verse": 1,
      "text": "ድሕሪ ደጊምሲ ሕንቅቕቲ ስውንቲ ኣይክትበሀልን ኢኺ እሞ፡ ኣቲ ድንግል ጓል ባቢሎን፡ ውረዲ ኣብ ሓመድ ከኣ ተቐመጢ፡ ኣቲ ጓል ከለዳውያን፡ ብዘይ ዝፋን ኣብ ምድሪ ተቐመጢ።"
    },
    {
      "verse": 2,
      "text": "መጥሓን ሐዚ እሞ ሓርጭ ጥሐኒ፡ ጒልባብኪ ቕልዒ፡ ነቲ ወለል ዚብል ዘፈር ክዳንኪ ሰብስቢ፡ ደናጉኺ ጥራዩ ጌርኪ ውሓይዝ ተሳገሪ።"
    },
    {
      "verse": 3,
      "text": "ዕርቃንኪ ይቀላዕ፡ ነውርኺ ኸኣ ይረኤ፡ ሕነ ኽፈዲ እየ፡ ዚገጥመለይ ከኣ ሓደ እኳ የልቦን።"
    },
    {
      "verse": 4,
      "text": "ስም እቲ ተበጃዊናስ እግዚኣብሄር ጐይታ ሰራዊት፡ ናይ እስራኤል ቅዱስ እዩ።"
    },
    {
      "verse": 5,
      "text": "ኣቲ ጓል ከለዳውያን፡ ድሕሪ ደጊም እትየ መንግስትታት ኣይክትበሀልን ኢኺ እሞ፡ ስቕ ኢልኪ ተቐመጢ፡ ናብ ጸልማት ኣግልሲ።"
    },
    {
      "verse": 6,
      "text": "ኣብ ህዝበይ ኰሬኹ፡ ርስተይ ፈንፈንኩ፡ ኣብ ኢድኪ ኸኣ ኣሕሊፈ ሀብክዎም። ንስኺ ኣይምሐርክዮምን፡ ኣርዑትኪ ኣብቶም ኣረገውቲ ኣዚኺ ኣኽበድኪ።"
    },
    {
      "verse": 7,
      "text": "ነዚ ኣብ ልብኺ ኸየንበርኪ፡ ብናይ መወዳእታውን ከይሐሰብኪ፡ ኣነስ ኰታ ንዂሉ ጊዜ እትየ እየ፡ በልኪ።"
    },
    {
      "verse": 8,
      "text": "እምበኣርሲ ኣቲ ግዲ ዂሉ ዜብልኪ፡ ብልብኺ ኸኣ፡ ኣነ ጥራይ እየ እምበር፡ ብጀካይ ካልእ የልቦን፡ ኣነስ ከቶ ኣይክምብሉን፡ ስእነት ውሉድውን ኣይክፈልጥን እየ፡ እትብሊ ተሰዋኒት፡ ነዚ ስምዒ፡"
    },
    {
      "verse": 9,
      "text": "ክልቲኣተን፡ ስእነት ውሉድን ምብልውናን፡ ብሓንቲ መዓልቲ ድንገት ኪመጻኺ እየን። ምንም እኳ ጥንቊልናኺ እንተ በዝሔ፡ ምዕዛምኪውን እንተ በርትዔ፡ ብምሉእ መስፈር ኪመጻኺ እየን።"
    },
    {
      "verse": 10,
      "text": "ብኽፍኣትኪ ተወከልኪ እሞ፡ ዚርኣየኒ የልቦን፡ በልኪ፡ ጥበብክን ፍልጠትክን ኣስሐተኪ፡ ብልብኺውን፡ ኣነ እምበር፡ ብጀካይ ካልእ የልቦን፡ በልኪ።"
    },
    {
      "verse": 11,
      "text": "ስለዚ ኽትዕዝምዮ ዘይከኣለኪ መዓት ኪመጻኪ፡ ከተዝብልዮ ዘይኰነልኪ መከራ ኸኣ ኪወርደኪ እዩ፡ ዘይፈለጥክዮ ጥፍኣት ድማ ብድንገት ኪወርደኪ እዩ።"
    },
    {
      "verse": 12,
      "text": "ምናልባሽ እንተ ጠቐመኪ፡ ምናልባሽ እንተ ኣሰምበደክስ፡ ነቲ ኻብ ንእስነትኪ ጀሚርኪ ዝጸዐርክሉ ጥንቈላን ብዝሒ ኣስማትክን ሒዝኪ፡ ቕረቢ።"
    },
    {
      "verse": 13,
      "text": "ብብዝሒ ምኽርታትኪ ደኸምኪ፡ እቶም ፈለጥቲ ትእምርቲ ሰማይን እቶም ቈጸርቲ ኸዋኽብትን እቶም ነቲ ኣብ ሰሰርቂ ወርሒ ዚረኽበኪ ዚነግሩኽን ይተንስኡ እሞ የድሕኑኺ።"
    },
    {
      "verse": 14,
      "text": "እንሆ፡ ንሳቶም ከም ሓሰር እዮም፡ ሓዊ የንድዶም፡ ካብ ሓይሊ ሃልሃልታ ንነፍሶም ኣየድሕንዋን። ጓህሪ ንምስሓን ዚኸውን፡ ሓዊ ኸኣ ኣብ ቅድሚኡ ኾፍ ንምባል ዚኸውን ኣይኪህሉን እዩ።"
    },
    {
      "verse": 15,
      "text": "ዕድል እቶም ዝጸዐርክሎም ከምዚ ኪኸውን እዩ። እቶም ካብ ንእስነትኪ ጀሚሮም መናግድትኺ ዝነበሩ መመገዶም ጸው ኪብሉ እዮም፡ ሓደ እኳ ዜድሕነኪ የልቦን።"
    }
  ]
}