{
  "book": "Psalms",
  "bookNumber": 19,
  "chapter": 111,
  "verses": [
    {
      "verse": 1,
      "text": "Halleluja! Jeg vil prise Herren av hele mitt hjerte i de oppriktiges råd og i menigheten."
    },
    {
      "verse": 2,
      "text": "Store er Herrens gjerninger, søkt av alle dem som har lyst til dem."
    },
    {
      "verse": 3,
      "text": "Høyhet og herlighet er hans gjerning, og hans rettferdighet står fast til evig tid."
    },
    {
      "verse": 4,
      "text": "Han har sørget for at hans undergjerninger minnes. Herren er nådig og barmhjertig."
    },
    {
      "verse": 5,
      "text": "Han har gitt mat til dem som frykter ham. Til evig tid kommer han sin pakt i hu."
    },
    {
      "verse": 6,
      "text": "Han har vist sitt folk sine gjerningers kraft ved å gi dem hedningers arv."
    },
    {
      "verse": 7,
      "text": "Hans henders gjerninger er sannhet og rett, alle hans bud er trofaste,"
    },
    {
      "verse": 8,
      "text": "de er grunnfestet for all tid, for evighet, de er gjort i sannhet og rettvishet."
    },
    {
      "verse": 9,
      "text": "Han har sendt sitt folk forløsning, han har fastsatt sin pakt for evig. Hans navn er hellig og forferdelig."
    },
    {
      "verse": 10,
      "text": "Å frykte Herren er begynnelsen til visdom. God forstand har alle de som gjør etter hans bud. Hans pris varer til evig tid."
    }
  ]
}