{
  "book": "Psalms",
  "bookNumber": 19,
  "chapter": 94,
  "verses": [
    {
      "verse": 1,
      "text": "Du hevnens Gud! Herre, du hevnens Gud, åpenbar deg i herlighet!"
    },
    {
      "verse": 2,
      "text": "Reis deg, du jordens dommer! La gjengjeldelse komme over de stolte!"
    },
    {
      "verse": 3,
      "text": "Hvor lenge skal de onde, Herre, hvor lenge skal de onde fryde seg?"
    },
    {
      "verse": 4,
      "text": "De spruter ut en strøm av ord, de fører frekk tale. Alle de som gjør urett, taler store ord."
    },
    {
      "verse": 5,
      "text": "Ditt folk, Herre, knuser de, og din arv plager de."
    },
    {
      "verse": 6,
      "text": "Enken og den fremmede slår de i hjel, farløse myrder de."
    },
    {
      "verse": 7,
      "text": "Og de sier: Herren ser det ikke, Jakobs Gud gir ikke akt."
    },
    {
      "verse": 8,
      "text": "Forstå da, dere uforstandige blant folket! Og dere dårer, når skal dere bli vise?"
    },
    {
      "verse": 9,
      "text": "Han som plantet øret, skulle han ikke høre? Han som skapte øyet, skulle han ikke se?"
    },
    {
      "verse": 10,
      "text": "Han som refser hedningene, skulle han ikke straffe - han som gir menneskene forstand?"
    },
    {
      "verse": 11,
      "text": "Herren kjenner menneskenes tanker, han vet at de bare er tomhet."
    },
    {
      "verse": 12,
      "text": "Salig er den mannen som du tukter, Herre, den du gir lærdom av din lov,"
    },
    {
      "verse": 13,
      "text": "for å gi ham ro for onde dager, inntil det blir gravd en grav for den ugudelige."
    },
    {
      "verse": 14,
      "text": "For Herren skal ikke forkaste sitt folk og ikke forlate sin arv."
    },
    {
      "verse": 15,
      "text": "For dommen skal vendes til rettferdighet, og alle de oppriktige av hjertet skal gi den medhold."
    },
    {
      "verse": 16,
      "text": "Hvem reiser seg for meg mot de onde? Hvem stiller seg fram for meg mot dem som gjør urett?"
    },
    {
      "verse": 17,
      "text": "Dersom ikke Herren var min hjelp, ville min sjel snart bo i stillhetens land."
    },
    {
      "verse": 18,
      "text": "Om jeg måtte si: Min fot vakler! - da holder din miskunnhet meg oppe, Herre!"
    },
    {
      "verse": 19,
      "text": "Når mine urolige tanker blir mange i mitt hjerte, da fryder din trøst min sjel."
    },
    {
      "verse": 20,
      "text": "Har vel fordervelsens domstol noe samfunn med deg, der hvor de skaper urett under skinn av rett?"
    },
    {
      "verse": 21,
      "text": "Skarevis slår de seg sammen mot den rettferdige sjel. Ved deres dom blir det utgytt uskyldig blod."
    },
    {
      "verse": 22,
      "text": "Da blir Herren meg en borg, min Gud er min tilfluktsklippe."
    },
    {
      "verse": 23,
      "text": "Han lar deres urett komme tilbake over dem selv, han utrydder dem for deres ondskaps skyld. Ja, Herren vår Gud skal utrydde dem."
    }
  ]
}