{
  "book": "Job",
  "bookNumber": 18,
  "chapter": 30,
  "verses": [
    {
      "verse": 1,
      "text": "ሕጂ ግና እቶም ብዕድመ ዚንእሱኒ፡ ነቦታቶም ምስቶም ኣኽላባት መጓሰይ እኳ ዘይመሕበርክዎም፡ ይንዕቁኒ ኣለው።"
    },
    {
      "verse": 2,
      "text": "እዞም ናብ ዝበሰለ ዕድመ ኺበጽሑ ዘይኽእሉ ሰባት፡ ሓይሊ ኣእዳዎም እንታይ ኪጠቕመኒ እዩ?"
    },
    {
      "verse": 3,
      "text": "ብስእነትን ጥሜትን ዝማህመኑ እዮም፡ ነቲ ኻብ ቀደም ዝጸመወን በረኻ ዝዀነን ንቑጽ ምድሪ ይግህጽዎ።"
    },
    {
      "verse": 4,
      "text": "ካብ ጥቓ ቘጥቋጥ ቈጽሊ ኣምዒ ይቕንጥቡ፡ ሱር ቈጥቋጥ ምግቦም ይገብሩ።"
    },
    {
      "verse": 5,
      "text": "ካብ ሕብረት ሰብ ይስጐጉ፡ ከም ንሰራቒ ደድሕሪኦም የድህዩ።"
    },
    {
      "verse": 6,
      "text": "ኣብ ዜፍርህ ጋግ፡ ኣብ ጒድጓድ ምድርን ኣብ ማእከል ከውሕን ይነብሩ፡"
    },
    {
      "verse": 7,
      "text": "ኣብ ማእከል ዱር ኰይኖም ይጭድሩ፡ ኣብ ትሕቲ እሾዂ ይእከቡ።"
    },
    {
      "verse": 8,
      "text": "ውሉድ ደናቚርቲ፡ ስም ዜብሉ ዓሌት፡ ተገሪፎም ካብ ሃገር እተሰጉ ኣዮም።"
    },
    {
      "verse": 9,
      "text": "ሕጂ ኣነ መድረፊኦም ኰንኩ፡ መዛረቢኦምውን ገበሩኒ፡"
    },
    {
      "verse": 10,
      "text": "ርሒቕ ካባይ ሀዲሞም ይፍንፍኑኒ፡ ናብ ገጸይ ጡፍ ኪብሉ ኣይሐፍሩን እዮም።"
    },
    {
      "verse": 11,
      "text": "ገመደይ ፈቲሑ ኣዋረደኒ እሞ፡ ነቲ ልጓም ኣብ ቅድመይ ደርበይዎ።"
    },
    {
      "verse": 12,
      "text": "እዞም ሕማቓት ኣብ የማነይ ይትንስኡ፡ ነእጋረይ ይደፍእወን፡ ናይ ጥፍኣት መገዶም ኣብ ልዕለይ ይድርብዩ ኣለው።"
    },
    {
      "verse": 13,
      "text": "ንመገደይ የፍርስዋ ኣለው፡ ንርእሶም እኳ ረዲኤት ዜብሎምስ፡ ንጥፍኣተይ ይተሓጋገዙ።"
    },
    {
      "verse": 14,
      "text": "ብገፊሕ ነቓዕ ከም ዚኣትው ዀይኖም ይመጹኒ፡ ብፍሩስ መካበብያ ኣንካራርዮም ይኣትው።"
    },
    {
      "verse": 15,
      "text": "ስምባደ ይወርደኒ፡ ከም ህቦብላ ዀይኖም ንኽብረይ የባርርዎ፡ ጣዕሚ ንብረተይ ከም ደበና ሐሊፉ።"
    },
    {
      "verse": 16,
      "text": "ሕጂ ድማ ነፍሰይ ኣብ ውሽጠይ ትመክኽ ኣላ፡ መዓልትታት መከራ ሒዘናኒ፡"
    },
    {
      "verse": 17,
      "text": "ብለይቲ ኣዕጽምተይ ይንደል፡ ዚቐራጥመኒ ቓንዛ ኣይዐርፍን እዩ።"
    },
    {
      "verse": 18,
      "text": "ብብርቱዕ ሓይሊ ሕማመይ ክዳነይ ተበላሽዩ፡ ከም ክሳድ ቀምሸይ ጠሚሩኒ።"
    },
    {
      "verse": 19,
      "text": "ናብ ጭቃ ደርብዩኒ፡ ከም መሬትን ሓመዂስትን ኰይነ።"
    },
    {
      "verse": 20,
      "text": "ናባኻ እምህለል ኣሎኹ፡ ኣይትመልሰለይን፡ ደው ኢለ እኔኹ፡ ተኲርካ ትጥምተኒ ኣሎኻ።"
    },
    {
      "verse": 21,
      "text": "ናብ ጨካን ተለዊጥካኒ፡ በታ ብርትዕቲ ኢድካ ትቃወመኒ ኣሎኻ።"
    },
    {
      "verse": 22,
      "text": "ሓፍ ኣቢልካ ብህቦብላ ትሕልፈኒ፡ ብሸምቦባውን ተምክኸኒ ኣሎኻ።"
    },
    {
      "verse": 23,
      "text": "ኤረ ናብቲ ዂሎም ህያዋን ዚእከቡሉ ቤት፡ ናብ ሞት ከም እትወስደኒ እፈልጥ ኣሎኹ።"
    },
    {
      "verse": 24,
      "text": "ግናኸ ዚወድቕ ሰብዶ ኢዱ ኣይዝርግሕን? ወይስ ጥፍኣት ዝመጾዶ ኣየእውን እዩ?"
    },
    {
      "verse": 25,
      "text": "ኣነስ ነቲ ጽጉም መዓልቲ ዝረኸቦዶ እበኽየሉ ኣይነበርኩን? ንድኻውን ነፍሰይ ትሐዝነሉዶ ኣይነበረትን?"
    },
    {
      "verse": 26,
      "text": "እንሆ፡ ራህዋ ንምርካብ ተስፋ ገበርኩ፡ ግናኸ ጸበባ መጸ፡ ብርሃን ተጸቤኹ፡ ግናኸ ጸልማት መጸ።"
    },
    {
      "verse": 27,
      "text": "ኣምዑተይ ይፈልሕ እሞ ኣይዐርፍን እዩ፡ መዓልትታት መከራ ተጓኒፈናኒ።"
    },
    {
      "verse": 28,
      "text": "ብዘይ ጸሓይ ጸሊመ እዘውር ኣሎኹ፡ ኣብ ማእከል ማሕበርውን እናተሳእኩ ኤእዊ።"
    },
    {
      "verse": 29,
      "text": "ንወኻሩ ሓወን፡ ንሰገናትውን መሓዝኤን ኰንኩ።"
    },
    {
      "verse": 30,
      "text": "ቈርበተይ ጸሊሙ፡ ካብ ስጋይውን ተፋላልዩ፡ ኣዕጽምተይ ከኣ ብረስኒ ሐሪሩ።"
    },
    {
      "verse": 31,
      "text": "ስለዚ መሰንቆይ ናብ ሓዘን፡ ዕንዱረይ ከኣ ናብ ደሃይ ብኽያት ተለዊጡ።"
    }
  ]
}