{
  "book": "Genesis",
  "bookNumber": 1,
  "chapter": 23,
  "verses": [
    {
      "verse": 1,
      "text": "የሣራም ዕድሜ መቶ ሀያ ሰባት ዓመት ሆነ።"
    },
    {
      "verse": 2,
      "text": "በቂርያትአርባቅም ሞተች፤ እርስዋም በከነዓን ምድር ያለች ኬብሮን ናት፤ አብርሃምም ለሣራ ሊያዝንላትና ሊያለቅስላት ተነሣ።"
    },
    {
      "verse": 3,
      "text": "አብርሃምም ከሬሳው አጠገብ ተነሣ፥"
    },
    {
      "verse": 4,
      "text": "ለኬጢ ልጆችም እንዲህ ሲል ተናገረ። እኔ በእናንተ ዘንድ ስደተኛና መጻተኛ ነኝ፤ በእናንተ ዘንድ የመቃብር ርስት ስጡኝ፥ ሬሳዬንም ከፊቴ ልቅበር።"
    },
    {
      "verse": 5,
      "text": "የኬጢ ልጆችም ለአብርሃም መለሱ፥ አሉትም።"
    },
    {
      "verse": 6,
      "text": "ጌታ ሆይ፥ ስማን፤ አንተ በእኛ መካከል ከእግዚአብሔር አለቃ ነህ፤ ከመቃብር ስፍራችን በመልካሙ ቦታ ሬሳህን ቅበር፤ ሬሳህን ትቀብር ዘንድ ከእኛ መቃብሩን የሚከለክልህ የለም።"
    },
    {
      "verse": 7,
      "text": "አብርሃምም ተነሣ፥ ለምድሩ ሕዝብም፥ ለኬጢ ልጆች፥ ሰገደ።"
    },
    {
      "verse": 8,
      "text": "እንዲህም አላቸው። ሬሳዬን ከፊቴ እንድቀብር ከወደዳችሁስ ስሙኝ፥ ከሰዓር ልጅ ከኤፍሮንም ለምኑልኝ፤"
    },
    {
      "verse": 9,
      "text": "በእርሻው ዳር ያለችውን ድርብ ክፍል ያላትን ዋሻውን በሙሉ ዋጋ በመካከላችሁ ይስጠኝ፥ መቃብሩ የእኔ ርስት እንዲሆን።"
    },
    {
      "verse": 10,
      "text": "ኤፍሮንም በኬጢ ልጆች መካከል ተቀምጦ ነበር፤ የኬጢ ሰው ኤፍሮንም የኬጢ ልጆችና ወደ ከተማ የሚገቡ ሁሉ ሲሰሙ ለአብርሃም እንዲህ ሲል መለሰለት።"
    },
    {
      "verse": 11,
      "text": "አይደለም፥ ጌታዬ፥ ስማኝ፤ እርሻውን ሰጥቼሃለሁ በእርሱም ዳር ያለውን ዋሻ ሰጥቼሃለሁ፤ በወገኔ ልጆች ፊት ሰጥቼሃለሁ፤ ሬሳህን ቅበር።"
    },
    {
      "verse": 12,
      "text": "አብርሃምም በአገሩ ሰዎች ፊት ሰገደ፤"
    },
    {
      "verse": 13,
      "text": "የአገሩ ሰዎችም ሲሰሙ ለኤፍሮን እንዲህ ሲል ተናገረ። ነገሬን ትሰማ ዘንድ እለምንሃለሁ፤ የእርሻውን ዋጋ እሰጥሃለሁ፤ አንተም ከእኔ ዘንድ ውሰድ፥ ሬሳዬንም በዚያ እቀብራለሁ።"
    },
    {
      "verse": 14,
      "text": "ኤፍሮንም ለአብርሃም እንዲህ ሲል መለሰለት።"
    },
    {
      "verse": 15,
      "text": "ጌታዬ ሆይ፥ እኔን ስማኝ፤ የአራት መቶ ሰቅል ዋጋ ምድር በእኔና በአንተ መካክለ ምንድር ነው? ሬሳህንም ቅበር።"
    },
    {
      "verse": 16,
      "text": "አብርሃምም የኤፍሮንን ነገር ሰማ፤ አብርሃምም በኬጢ ልጆች ፊት የነገረውን አራት መቶ ሰቅል መዝኖ ለኤፍሮን ሰጠው፤ ብሩም ለመሸጫ ለመለወጫ የሚተላለፍ ነበረ።"
    },
    {
      "verse": 17,
      "text": "በመምሬ ፊት ያለው ባለድርብ ክፍል የሆነው የኤፍሮን እርሻ ለአብርሃም ጸና፤"
    },
    {
      "verse": 18,
      "text": "እርሻው በእርሱም ያለው ዋሻው፥ በእርሻውም ውስጥ በዙሪያውም ያለው እንጨት ሁሉ በኬጢ ልጆችና በከተማይቱ በር በሚገቡ ሁሉ ፊት ለአብርሃም ርስቱ ሆነ።"
    },
    {
      "verse": 19,
      "text": "ከዚህም በኋላ ኬብሮን በምትባል በመምሬ ፊት በከነዓን ምድር ባለው እርሻ ባለ ድርብ ክፍል በሆነው ዋሻ ውስጥ አብርሃም ሚስቱን ሣራን ቀበረ።"
    },
    {
      "verse": 20,
      "text": "እርሻውና በእርሱ ያለው ዋሻው በኬጢ ልጆች ዘንድ ለአብርሃም የመቃብር ርስት ሆኖ ጸና።"
    }
  ]
}