{
  "book": "Ezekiel",
  "bookNumber": 26,
  "chapter": 34,
  "verses": [
    {
      "verse": 1,
      "text": "ከምዚ ዚብል ቃል እግዚኣብሄር ከኣ መጸኒ፣"
    },
    {
      "verse": 2,
      "text": "ኣታ ወዲ ሰብ፣ ኣብቶም ጓሶት እስራኤል ተነበ፣ ነቶም ጓሶት ተነበየሎም፣ እግዚኣብሄር ኣምላኽ ከምዚ ይብል ኣሎ፣ ኢልካውን ንገሮም፣ ነቶም ንርእሶም ጥራይ ዚጓስዩ ጓሶት እስራኤል ወይለኦም። እቶም ጓሶትሲ ነተን ኣባጊዕዶ ኣይኰኑን ዚጓስዩ∶"
    },
    {
      "verse": 3,
      "text": "ነቲ ስቡሕ ትበልዑ፣ ጸምሪ ትኽደኑ፣ ነቲ ዝሰብሔ ትሐርዱ፣ ነቲ መጓሰ ግና ኣይትኣልዩን።"
    },
    {
      "verse": 4,
      "text": "ንዝሐመቓ ኣየበርታዕኩምን፣ ንዝሐመመት ኣይፈወስኩምን፣ ንተሰብረት ኣይዘነንኩምን፣ ንተባረረት ኣይመለስኩምን፣ ንዝጠፍኤት ኣይደሌኹምን፣ ብሓይልን ብትርን ደኣ ገዛእኩምወን።"
    },
    {
      "verse": 5,
      "text": "ጓሳ ስለ ዘይነበረን ፋሕ በላ፣ ንዅሎም ኣራዊት መሮር ከኣ ብልዒ ዀና፣ ፋሕውን በላ።"
    },
    {
      "verse": 6,
      "text": "ኣባጊዔይ ኣብ ኵሉ ኣኽራንን ኣብ ኵሉ ነነዋሕቲ ዅርባታትን ተባረራ፣ ኣብ ኵሉ ዝባን ምድሪ ፋሕ በላ፣ ግደን ዚገብርን ዚደልየንን ከኣ የልቦን።"
    },
    {
      "verse": 7,
      "text": "ስለዚ፣ ኣቱም ጓሶት፣ ቃል እግዚኣብሄር ስምዑ፣"
    },
    {
      "verse": 8,
      "text": "ኣነ ህያው እየ፣ ይብል እግዚኣብሄር ኣምላኽ፣ ኣባጊዔይ ተዘሪፈን፣ ኣባጊዔይ ከኣ ንዅሎም ኣራዊት መሮር ብልዒ ዀይነን፣ እቶም ጓሶት ኣይነበሩን፣ ጓሶተይ ግዲ ኣባጊዔይ ኣይገበሩን፣ እቶም ጓሶት ንርእሶም ጓሰዩ እምበር፣ ነባጊዔይሲ ኣይጓሰይወንን እዮም እሞ፣"
    },
    {
      "verse": 9,
      "text": "ስለዚ፣ ኣቱም ጓሶት፣ ቃል እግዚኣብሄር ስምዑ፣"
    },
    {
      "verse": 10,
      "text": "እግዚኣብሄር ኣምላኽሲ እንሆ፣ ኣብቶም ጓሶት እጥልቕ ኣሎኹ፣ ኣባጊዔይ ከኣ ካብ ኢዶም ክደልየን እየ። እቶም ጓሶት መሊሶም ንርእሶም ከይጓስዩስ፣ ጕስነት ኣባጊዔይ ከሕድጎም እየ። ድሕርዚ ቐለቦም ከይዀና ድማ፣ ካብ ኣፎም ክምንዝዔን እየ፣ ይብል ኣሎ።"
    },
    {
      "verse": 11,
      "text": "ስለዚ እግዚኣብሄር ኣምላኽ ከምዚ ይብል ኣሎ፣ እኔኹ ኣነ ባዕለይ፣ ኣነ ነተን ኣባጊዔይ ክኣልየንን ክደልየንን እየ።"
    },
    {
      "verse": 12,
      "text": "ከምቲ ጓሳ፣ በታ እተን መጓሲኡ ፋሕ ዚብላላ መዓልቲ ኣብ ማእከል ኣባጊዑ ጸኒሑ ዚደልየን፣ ከምኡ ድማ ኣነ ነባጊዔይ ክደልየን፣ ካብ ኵሉ እቲ ብመዓልቲ ደበናን ጸልማትን ፋሕ ኢለናኦ ዝነበራ ቦታ ኸኣ ከናግፈን እየ።"
    },
    {
      "verse": 13,
      "text": "ካብ ህዝብታት ከውጽኤን፣ ካብ ሃገራት ክእክበን፣ ናብ ሃገረን ድማ ክመልሰን፣ ኣብ ኣኽራን እስራኤልን ኣብ ጥቓ ወሓዚ መስኖ ኣብቲ ሰብ ዚነብረሉ ኵሉ ቦታ እታ ሃገርን ክጓስየን እየ።"
    },
    {
      "verse": 14,
      "text": "ኣብ ልሙዕ መጓስዪ ኸውፍረን እየ፣ ደምቢኤን ከኣ ኣብቲ ነዋሕቲ ኣኽራን እስራኤል ኪኸውን እዩ። ኣብኡ ኣብ ጽቡቕ ደምበ ኺድቅሳ፣ ኣብ ስቡሕ መውፈሪ ኣብ ኣኽራን እስራኤል ኪጓሰያ እየን።"
    },
    {
      "verse": 15,
      "text": "ኣነ ባዕለይ ነባጊዔይ ኸውፍረን ባዕለይ ድማ ከስፍረን እየ፣ ይብል እግዚኣብሄር ኣምላኽ።"
    },
    {
      "verse": 16,
      "text": "ዝጠፍኤት ክደሊ፣ እተባረረት ክመልስ፣ እተሰብረት ክዘንን፣ ዝሐመቐት ከኣ ከጽንዕ፣ ነታ ዝሰብሔትን ዝበርትዔትን ግና ከጥፍእ፣ ብፍርዲውን ክጓስየን እየ።"
    },
    {
      "verse": 17,
      "text": "እግዚኣብሄር ኣምላኽ ከምዚ ይብል ኣሎ፣ ኣትን ኣባጊዔይ፣ እንሆ፣ ኣነ ኣብ መንጎ በጊዕን በጊዕን፣ ኣብ መንጎ ደዓውልን ደባሉን ክፈርድ እየ።"
    },
    {
      "verse": 18,
      "text": "ነቲ ካብ መውዓሊኹም ዝተረፈ በእጋርኩም እትረግጽዎስ፣ ኣብቲ ልሙዕ ሸኻ ምውዓልዶ ውሒድኩም እዩ∶ ነቲ ዝተረፈ ማይ ምስታይዶ ውሒድኩም እዩ∶"
    },
    {
      "verse": 19,
      "text": "እሞ እተን ኣባጊዔይሲ እቲ በእጋርኩም እተረግጸዶ ኺበልዓ፣ እቲ ኣእጋርኩም ዝዘረጎስ ኪሰትያ እየን∶"
    },
    {
      "verse": 20,
      "text": "ስለዚ እግዚኣብሄር ኣምላኽ ከምዚ ይብል ኣሎ፣ እኔኹ፣ ኣነ ባዕለይ ኣብ መንጎ እተን ስቡሓት ኣባጊዕን እተን ዓባሩ ኣባጊዕን ክፈርድ እየ።"
    },
    {
      "verse": 21,
      "text": "ንዅለን እተን ዝሐመቓ ዘበላ ኽሳዕ ሰጕጕኩም ፋሕ እተብልወን፣ ብጐድንን ብመንኩብን ስለ ዝጐነጽኩምወን፣ በቕርንትኹም ድማ ስለ ዝወጋእኩምወን፣"
    },
    {
      "verse": 22,
      "text": "ስለዚ ኣነ ነባጊዔይ፣ ድሕርዚ ንዘመተ ኸይውፈያ፣ ከድሕነን ኣብ መንጎ በጊዕን በጊዕን ከኣ ክፈርድ እየ።"
    },
    {
      "verse": 23,
      "text": "ኣነ ኸኣ ዚጓስየን ሓደ ጓሳ፣ ዳዊት ባርያይ፣ ከተንስኣለን እየ። ንሱ ኺጓስየን፣ ጓሳኤን ድማ ኪኸውን እዩ።"
    },
    {
      "verse": 24,
      "text": "ኣነ እግዚኣብሄር ኣምላኾም ክኸውን እየ፣ ዳዊት ባርያይውን ኣብ ማእከሎም መስፍን ኪኸውን እዩ፣ ኣነ እግዚኣብሄር ተዛሪበ ኣሎኹ።"
    },
    {
      "verse": 25,
      "text": "ኣነ ምሳታተን ኪዳን ሰላም ክኣቱ፣ ንኽፉኣት ኣራዊት ካብ ሃገር ከጥፍኦም እየ። ንሳተን ከኣ ኣብ በረኻ ሀዲኤን ኪነብራ፣ ኣብ ዱርውን ኪድቅሳ እየን።"
    },
    {
      "verse": 26,
      "text": "ኣነ ኸኣ ንእኤንን ነቲ ኣብ ዙርያ ኹርባይ ዘሎ ቦታን ንበረኸት ክገብሮም እየ። ዝናም ብግዜኡ ኸውርድ እየ፣ ዝናም በረኸትውን ኪኸውን እዩ።"
    },
    {
      "verse": 27,
      "text": "ኦም መሮር ፍሪኡ ኼፍሪ እዩ፣ ምድሪውን ብቝላ ኽትህብ እያ፣ ኣብ ሃገሮም ከኣ ሀዲኦም ኪነብሩ እዮም። ኣነ ሰንሰለት ኣርዑቶም ምስ ሰበርኩ፣ ካብ ኢድ እቶም ባሮት ዝገበርዎም ከኣ ምስ ኣናገፍክዎም፣ ሽዑ ኣነ እግዚኣብሄር ምዃነይ ኪፈልጡ እዮም።"
    },
    {
      "verse": 28,
      "text": "ድሕርዚ ዘመተ ህዝብታት ኣይኪዀኑን እዮም፣ ኣራዊት ምድሪ ኸኣ ኣይኪበልዕዎምን እዮም። ኤረ ሀዲኦም ኪነብሩ እዮም፣ ዜፍርሆምውን የልቦን።"
    },
    {
      "verse": 29,
      "text": "ንናእዳ ዚዀኖም ተኽሊ ኸተንስኣሎም እየ፣ ድሕርዚ ኸኣ ኣብታ ሃገር ብጥሜት ኣይኪጠፍኡን፣ ድሕሪ ደጊም ድማ ጸርፊ ህዝብታት ኣይኪጾሩን እዮም።"
    },
    {
      "verse": 30,
      "text": "ኣነ እግዚኣብሄር ኣምላኾምሲ ምሳታቶም ከም ዝዀንኩ ኺፈልጡ እዮም፣ ይብል እግዚኣብሄር ኣምላኽ።"
    },
    {
      "verse": 31,
      "text": "ኣቱም ኣባጊዔይ፣ ኣባጊዕ መውፈረይ፣ ንስኻትኩም ሰብ ኢኹም፣ ኣነ ኸኣ ኣምላኽኩም እየ፣ ይብል እግዚኣብሄር ኣምላኽ።"
    }
  ]
}