{
  "book": "Ezekiel",
  "bookNumber": 26,
  "chapter": 6,
  "verses": [
    {
      "verse": 1,
      "text": "ከምዚ ዚብል ቃል እግዚኣብሄር ድማ መጸኒ፣"
    },
    {
      "verse": 2,
      "text": "ኣታ ወዲ ሰብ፣ ገጽካ ናብ ኣኽራን እስራኤል ኣቕንዓዮ እሞ ተነበየለን፣"
    },
    {
      "verse": 3,
      "text": "በልውን፣ ኣትን ኣኽራን እስራኤል፣ ቃል እግዚኣብሄር ኣምላኽ ስምዓ፣ እግዚኣብሄር ኣምላኽ ነኽራንን ንዅርባታትን ንሽንጭሮታትን ንለሴታትን ከምዚ ይብል ኣሎ፣ እኔኹ ኣነ፣ እወ ኣነ ሰይፊ ኸምጽኣልኩም፣ ነቲ በረኽቲ ስፍራታትኩም ከጥፍኦ እየ።"
    },
    {
      "verse": 4,
      "text": "መሰውኢታትኩም ኪፈርስ፣ እቲ ናይ ጸሓይ ኣዕኑድኩም ድማ ኪሰባበር፣ ነቶም ውጕኣትኩም ከኣ ኣብ ቅድሚ እቶም ጣኦታትኩም ከውድቖም እየ።"
    },
    {
      "verse": 5,
      "text": "ንሬሳታት ደቂ እስራኤል ኣብ ቅድሚ ጣኦታቶም ከንብሮ፣ ኣዕጽምትኹም ድማ ኣብ ዙርያ መሰውኢታትኩም ክዘርዎ እየ።"
    },
    {
      "verse": 6,
      "text": "መሰውኢታትኩም ምእንቲ ኺባድምን ኪዖኑን፣ ጣኦታትኩም ከኣ ኪስበርን ኪጠፍእን፣ ናይ ጸሓይ ኣዕኑድኩም፣ ንስኻትኩም ኣብ እትነብሩሉ ዘበለስ እተን ከተማታት ኪዖንዋ እየን፣ እቲ በረኽቲ ቦታታት ከኣ ኪፈርስ እዩ።"
    },
    {
      "verse": 7,
      "text": "ተወጊኦም ዚሞቱ ኣብ ማእከልኩም ኪወድቁ እዮም፣ ንስኻትኩም ከኣ ኣነ እግዚኣብሄር ምዃነይ ክትፈልጡ ኢኹም።"
    },
    {
      "verse": 8,
      "text": "ኣብ ሀሃገሩ ፋሕ ምስ በልኩም ግና፣ ኣብ ማእከል ህዝብታት ካብ ሰይፊ ዘምለጡ ሓያሎ ኺህልዉኹም እዮም፣ በዚ ኸምዚ ትርፊ ኽሐድገልኩም እየ።"
    },
    {
      "verse": 9,
      "text": "እቶም ዘምለጡ ሰብኩም ከኣ ነቲ ኻባይ ዝዘምበለ ዘማዊ ልቦምን፣ ነተን ኪዝምዋ ደድሕሪ ጣኦታቶም ዚኸዳ ኣዒንቶምን ምስ ሰባበርኩ፣ ኣብቲ ዘማረኽክዎም ኣብ ማእከል ህዝብታት ኰይኖም ኪዝክሩኒ እዮም። በቲ ብዅሉ ጽያፎም ዝገበርዎ እኩይ ከኣ ንርእሶም ኪፍንፍኑ እዮም።"
    },
    {
      "verse": 10,
      "text": "ኣነ እግዚኣብሄር ከም ዝዀንኩ ኸኣ ኪፈልጡ እዮም። እዚ መዓት እዚ ኸምጽኣሎም እየ ኢለ እተዛረብክዎ ብኸንቱ ኣይኰነን።"
    },
    {
      "verse": 11,
      "text": "እግዚኣብሄር ኣምላኽ ከምዚ ይብል ኣሎ፣ ብሰይፍን ብጥሜትን ብፌራን ኪወድቁ እዮም እሞ፣ ብኢድካ ኣጣቕዕ፣ ብእግርኻ ኸኣ ኰርደብደብ በል፣ ብዛዕባ ናይ ቤት እስራኤል ኵሉ እኩይ ጽያፍ ድማ፣ ኣየ፣ ወዮ፣ በል።"
    },
    {
      "verse": 12,
      "text": "እቲ ኣብ ርሑቕ ዘሎ ብፌራ ኺመውት፣ እቲ ኣብ ቀረባ ዘሎ ብፌራ ኺወድቕ፣ እቲ ዝተረፈን ተኸቢቡ ዘሎን ድማ ብጥሜት ኪመውት እዩ። በዚ ኸምዚ ቍጥዓይ ኣብታቶም ክፍጽም እየ።"
    },
    {
      "verse": 13,
      "text": "እቶም ውጉኣቶም ኣብ ማእከል ጣኦታቶም ኣብ ዙርያ መሰውኢታቶም፣ ኣብ ልዕሊ ዅሉ በረኽቲ ዅድዅዶታት፣ ኣብ ዅሉ ርእሲ ኣኽራን፣ ኣብ ትሕቲ ዅሉ ልሙዕ ገረብ፣ ኣብ ትሕቲ ዅሉ ብርቱዕ ቈጽሊ ዘለዎ ኣውሒ፣ ኣብ ማእከል እቲ ንዅሎም ጣኦታቶም ጥዑም መኣዛ ዝዐጠኑሉ ስፍራ ምስ ኰነ፣ ሽዑ ኣነ እግዚኣብሄር ምዃነይ ኪፈልጡ እዮም።"
    },
    {
      "verse": 14,
      "text": "ኣነ ኸኣ ኢደይ ክዝርግሓሎም እየ፣ ነታ ሃገር ድማ፣ ኣብ እተቐመጡ እኳ እንተ ተቐመጡ፣ ካብ በረኻ ዲብላታ እትገድድ ባዶን ጽምዋን ክገብራ እየ። ሽዑ ኣነ እግዚኣብሄር ምዃነይ ኪፈልጡ እዮም።"
    }
  ]
}