{
  "book": "Job",
  "bookNumber": 18,
  "chapter": 24,
  "verses": [
    {
      "verse": 1,
      "text": "ሁሉን ከሚችል አምላክ ዘንድ ዘመናት አልተሰወረምና  እርሱን የሚያውቁ ለምን ወራቱን አያዩም?"
    },
    {
      "verse": 2,
      "text": "የድንበሩን ምልክት የሚያፈርሱ አሉ፤  መንጋዎቹን በዝብዘው ያሰማራሉ።"
    },
    {
      "verse": 3,
      "text": "የድሀ አድጎቹን አህያ ይነዳሉ፤  የመበለቲቱን በሬ ስለ መያዣ ይወስዳሉ።"
    },
    {
      "verse": 4,
      "text": "ድሆቹን ከመንገዱ ያወጣሉ፤  የምድርም ችግረኞች ሁሉ ይሸሸጋሉ።"
    },
    {
      "verse": 5,
      "text": "እነሆ፥ በምድረ በዳ እንዳሉ እንደ ሜዳ አህዮች፥  መብልን ፈልገው ወደ ሥራቸው ይወጣሉ፤  ምድረ በዳውም ለልጆቻቸው መብልን ይሰጣቸዋል።"
    },
    {
      "verse": 6,
      "text": "እነዚያ በእርሻ ውስጥ እህላቸውን ያጭዳሉ፤  የበደለኛውንም ወይን ይቃርማሉ።"
    },
    {
      "verse": 7,
      "text": "ራቁታቸውን ያለ ልብስ ያድራሉ፥  በብርድ ጊዜ መጐናጸፊያ የላቸውም።"
    },
    {
      "verse": 8,
      "text": "ከተራሮች በሚወርድ ዝናብ ይረጥባሉ፤  መጠጊያም አጥተው ቋጥኙን ያቅፋሉ።"
    },
    {
      "verse": 9,
      "text": "ድሀ አደጉን ልጅ ከጡቱ የሚነጥሉ አሉ  ከችግረኛውም መያዣ ይወስዳሉ።"
    },
    {
      "verse": 10,
      "text": "ያለ ልብስ ራቁታቸውን ይሄዳሉ፤  ተርበውም ነዶዎችን ይሸከማሉ፤"
    },
    {
      "verse": 11,
      "text": "በእነዚህ ሰዎች አጥር ውስጥ ዘይት ያደርጋሉ፤  ወይንም ይጠምቃሉ፥ ነገር ግን ይጠማሉ።"
    },
    {
      "verse": 12,
      "text": "ከከተማውና ከገዛ ቤቶቻቸው ይባረራሉ፤  የልጆችም ነፍስ ለእርዳታ ትጮኻለች፤  እግዚአብሔር ግን ስንፍናቸውን አይመለከትም።"
    },
    {
      "verse": 13,
      "text": "እነዚህ በብርሃን ላይ የሚያምፁ ናቸው፤  መንገዱን አያውቁም፥ በጎዳናውም አይጸኑም።"
    },
    {
      "verse": 14,
      "text": "ነፍሰ ገዳዩም ሳይነጋ ማልዶ ይነሣል፤  ችግረኞችንና ድሆችን ይገድላል፤  በሌሊትም እንደ ሌባ ነው።"
    },
    {
      "verse": 15,
      "text": "የአመንዝራም ዓይን ድግዝግዝታን ይጠብቃል።  የማንም ዓይን አያየኝም ይላል፥  ፊቱንም ይሸፍናል።"
    },
    {
      "verse": 16,
      "text": "ቤቶቹን በጨለማ ይነድላሉ፤  በቀን ይሸሸጋሉ፤  ብርሃንም አያውቁም።"
    },
    {
      "verse": 17,
      "text": "የጥዋት ብርሃን ለእነርሱ ሁሉ እንደ ሞት ጥላ ነው፤  የሞትን ጥላ ድንጋጤ ያውቃሉና።"
    },
    {
      "verse": 18,
      "text": "እነርሱ በውኃ ፊት ላይ በርረው ያልፋሉ፤  እድል ፈንታቸውም በምድር ላይ የተረገመች ናት፤  ወደ ወይኑ ቦታ መንገድ አይዞሩም።"
    },
    {
      "verse": 19,
      "text": "ድርቅና ሙቀት የአመዳዩን ውኃ ያጠፋሉ፤  እንዲሁ ሲኦል በደለኞችን ታጠፋለች።"
    },
    {
      "verse": 20,
      "text": "ማኅፀን ትረሳዋለች፤  ትልም በደስታ ይጠባዋል፤  ዳግመኛም አይታሰብም፤  ክፋትም እንደ ዛፍ ይሰበራል።"
    },
    {
      "verse": 21,
      "text": "የማትወልደውን መካኒቱን ይበድላታል፤  ለመበለቲቱም በጎነት አያደርግም።"
    },
    {
      "verse": 22,
      "text": "ነገር ግን በኃይሉ ኃያላንን ይስባል፤  እርሱም በተነሣ ጊዜ ሰው በሕይወቱ አይታመንም።"
    },
    {
      "verse": 23,
      "text": "እግዚአብሔር በደኅና አኑሮአቸዋል፥  በዚያም ይታመናሉ፤  ዓይኖቹ ግን በመንገዳቸው ላይ ናቸው።"
    },
    {
      "verse": 24,
      "text": "ጥቂት ጊዜ ከፍ ከፍ ይላሉ፤  ይሄዳሉ፥ ይጠወልጋሉም፤  እንደ ሌሎች ሁሉ ይከማቻሉ፤  እንደ እሸትም ራስ ይቈረጣሉ።"
    },
    {
      "verse": 25,
      "text": "እንዲህስ ባይሆን ሐሰተኛ የሚያደርገኝ፥  ነገሬንስ እንደ ምናምን የሚያደርገው ማን ነው?"
    }
  ]
}